README.md
setup.py
testfilter/__init__.py
testfilter/filter.py
testfilter.egg-info/PKG-INFO
testfilter.egg-info/SOURCES.txt
testfilter.egg-info/dependency_links.txt
testfilter.egg-info/top_level.txt