Metadata-Version: 2.1
Name: testfilter
Version: 0.0.2
Summary: unittest 用例执行过滤， 可选择用例级别或用例标志进行过滤
Home-page: https://github.com/mocobk/testfilter
Author: mocobk
Author-email: mocobk@163.com
License: UNKNOWN
Platform: UNKNOWN
Classifier: Programming Language :: Python :: 3
Classifier: License :: OSI Approved :: MIT License
Classifier: Operating System :: OS Independent
